MANIFEST.in
README.rst
setup.py
docs/CONTRIBUTORS.rst
docs/HISTORY.rst
docs/LICENSE.GPL
docs/LICENSE.txt
seantis/__init__.py
seantis.kantonsrat.egg-info/PKG-INFO
seantis.kantonsrat.egg-info/SOURCES.txt
seantis.kantonsrat.egg-info/dependency_links.txt
seantis.kantonsrat.egg-info/entry_points.txt
seantis.kantonsrat.egg-info/namespace_packages.txt
seantis.kantonsrat.egg-info/not-zip-safe
seantis.kantonsrat.egg-info/requires.txt
seantis.kantonsrat.egg-info/top_level.txt
seantis/kantonsrat/__init__.py
seantis/kantonsrat/configure.zcml
seantis/kantonsrat/interfaces.py
seantis/kantonsrat/motion_providers.py
seantis/kantonsrat/profiles.zcml
seantis/kantonsrat/settings.py
seantis/kantonsrat/setuphandler.py
seantis/kantonsrat/sync.sh
seantis/kantonsrat/testing.py
seantis/kantonsrat/upgrades.py
seantis/kantonsrat/upgrades.zcml
seantis/kantonsrat/browser/__init__.py
seantis/kantonsrat/browser/base.py
seantis/kantonsrat/browser/configure.zcml
seantis/kantonsrat/browser/json_list.py
seantis/kantonsrat/browser/macros.py
seantis/kantonsrat/browser/membership_form.py
seantis/kantonsrat/browser/organization.py
seantis/kantonsrat/browser/organization_listing.py
seantis/kantonsrat/browser/reports.py
seantis/kantonsrat/browser/trigger_state.py
seantis/kantonsrat/browser/js/organization.js
seantis/kantonsrat/browser/templates/macros.pt
seantis/kantonsrat/browser/templates/organization.pt
seantis/kantonsrat/browser/templates/organization_listing.pt
seantis/kantonsrat/exports/__init__.py
seantis/kantonsrat/exports/addresses.py
seantis/kantonsrat/locales/seantis.kantonsrat.pot
seantis/kantonsrat/locales/de/LC_MESSAGES/plone.po
seantis/kantonsrat/locales/de/LC_MESSAGES/seantis.kantonsrat.po
seantis/kantonsrat/locales/de/LC_MESSAGES/seantis.people.po
seantis/kantonsrat/locales/de/LC_MESSAGES/z3c.formwidget.query.po
seantis/kantonsrat/profiles/default/browserlayer.xml
seantis/kantonsrat/profiles/default/catalog.xml
seantis/kantonsrat/profiles/default/controlpanel.xml
seantis/kantonsrat/profiles/default/jsregistry.xml
seantis/kantonsrat/profiles/default/metadata.xml
seantis/kantonsrat/profiles/default/registry.xml
seantis/kantonsrat/profiles/default/seantis.kantonsrat-default.txt
seantis/kantonsrat/profiles/default/types.xml
seantis/kantonsrat/profiles/default/types/Folder.xml
seantis/kantonsrat/profiles/default/types/Topic.xml
