Metadata-Version: 1.1
Name: seantis.kantonsrat
Version: 1.0.1
Summary: Specialized type and custom organisations for the Kantonsrat of Zug. 
Home-page: https://github.com/seantis/seantis.kantonsrat
Author: Seantis GmbH
Author-email: info@seantis.ch
License: GPL v2
Keywords: plone seantis people persons organizations positions kantonsrat
Platform: UNKNOWN
Classifier: Framework :: Plone
Classifier: Framework :: Plone :: 4.3
Classifier: Intended Audience :: Developers
Classifier: Topic :: Software Development :: Libraries :: Python Modules
Classifier: Programming Language :: Python
